<?xml version="1.0" encoding="UTF-8" standalone="no"?><Entities build="b112" majorVersion="9" minorVersion="2" modelPersistenceProviderPackage="PostgresPersistenceProviderPackage" revision="1" schemaVersion="1120" universal=""><ThingTemplates><ThingTemplate baseThingTemplate="GenericThing" description="" documentationContent="" effectiveThingPackage="ConfiguredThing" homeMashup="" inheritedValueStream="" lastModifiedDate="2022-07-07T04:04:36.452Z" name="MHI.Model.TT" projectName="MHI.Menu.User" tags="" thingPackage="" valueStream=""><Owner name="Administrator" type="User"/><avatar/><DesignTimePermissions><Create/><Read/><Update/><Delete/><Metadata/></DesignTimePermissions><RunTimePermissions/><VisibilityPermissions><Visibility/></VisibilityPermissions><ConfigurationTableDefinitions/><ConfigurationTables/><PropertyBindings/><RemotePropertyBindings/><RemoteServiceBindings/><RemoteEventBindings/><AlertConfigurations><AlertDefinitions name="para1"/></AlertConfigurations><ThingShape><PropertyDefinitions><PropertyDefinition aspect.cacheTime="0.0" aspect.dataChangeType="VALUE" aspect.isPersistent="true" baseType="STRING" category="" description="" isLocalOnly="false" name="para1" ordinal="2"/></PropertyDefinitions><ServiceDefinitions/><EventDefinitions/><ServiceMappings/><ServiceImplementations/><Subscriptions/></ThingShape><ImplementedShapes/><SharedConfigurationTables/><InstanceDesignTimePermissions><Create/><Read/><Update/><Delete/><Metadata/></InstanceDesignTimePermissions><InstanceRunTimePermissions/><InstanceVisibilityPermissions><Visibility/></InstanceVisibilityPermissions><ConfigurationChanges><ConfigurationChange changeAction="CREATE" changeReason="header : name : updated, projectName : updated&#10;properties : para1 : added, para1 : updated&#10;" timestamp="2022-07-07T04:04:36.452Z" user="Administrator"/></ConfigurationChanges></ThingTemplate></ThingTemplates></Entities>